glory/__init__.py
glory/glory.py
glory_ssh-0.1.5.dist-info/METADATA
glory_ssh-0.1.5.dist-info/WHEEL
glory_ssh-0.1.5.dist-info/entry_points.txt
glory_ssh-0.1.5.dist-info/top_level.txt
glory_ssh-0.1.5.dist-info/RECORD
