Metadata-Version: 2.2
Name: glory-ssh
Version: 0.1.5
Summary: 一个简单的SSH远程管理工具
Home-page: https://github.com/AbiesSaya/Glory
Author: AbiesAyakura
Author-email: qiandaoultra@gmail.com
Classifier: Programming Language :: Python :: 3
Classifier: License :: OSI Approved :: MIT License
Classifier: Operating System :: OS Independent
Requires-Python: >=3.6
Dynamic: author
Dynamic: author-email
Dynamic: classifier
Dynamic: description
Dynamic: description-content-type
Dynamic: home-page
Dynamic: requires-python
Dynamic: summary
